ImageGenPy
