Metadata-Version: 2.1
Name: ImageGenPy
Version: 0.0.14
Summary: Shitty python package for randomly generating images
Home-page: https://github.com/jclmnop/ImageGenPy
Download-URL: https://github.com/jclmnop/ImageGenPy/archive/refs/tags/v0.0.14.tar.gz
Author: jclmnop
Author-email: jclmnop@pm.me
License: MIT
Project-URL: Bug Tracker, https://github.com/jclmnop/ImageGenPy/issues
Classifier: Development Status :: 3 - Alpha
Classifier: Intended Audience :: Developers
Classifier: Topic :: Software Development :: Documentation
Classifier: License :: OSI Approved :: MIT License
Classifier: Programming Language :: Python :: 3
Classifier: Programming Language :: Python :: 3.9
License-File: LICENSE.txt
